MANIFEST.in
README.rst
setup.py
aliyun_python_sdk_core_emr_hack.egg-info/PKG-INFO
aliyun_python_sdk_core_emr_hack.egg-info/SOURCES.txt
aliyun_python_sdk_core_emr_hack.egg-info/dependency_links.txt
aliyun_python_sdk_core_emr_hack.egg-info/top_level.txt
aliyunsdkcore/__init__.py
aliyunsdkcore/client.py
aliyunsdkcore/endpoints.xml
aliyunsdkcore/request.py
aliyunsdkcore/acs_exception/__init__.py
aliyunsdkcore/acs_exception/error_code.py
aliyunsdkcore/acs_exception/error_msg.py
aliyunsdkcore/acs_exception/error_type.py
aliyunsdkcore/acs_exception/exceptions.py
aliyunsdkcore/auth/__init__.py
aliyunsdkcore/auth/md5_tool.py
aliyunsdkcore/auth/oss_signature_composer.py
aliyunsdkcore/auth/roa_signature_composer.py
aliyunsdkcore/auth/rpc_signature_composer.py
aliyunsdkcore/auth/sha_hmac1.py
aliyunsdkcore/auth/sha_hmac256.py
aliyunsdkcore/auth/url_encoder.py
aliyunsdkcore/http/__init__.py
aliyunsdkcore/http/format_type.py
aliyunsdkcore/http/http_request.py
aliyunsdkcore/http/http_response.py
aliyunsdkcore/http/method_type.py
aliyunsdkcore/http/protocol_type.py
aliyunsdkcore/profile/__init__.py
aliyunsdkcore/profile/region_provider.py
aliyunsdkcore/utils/__init__.py
aliyunsdkcore/utils/parameter_helper.py